Workbook

Sheet Portada
B2: Matriz RFP – Niveles, Ponderación y Escalas
B3: Entregable N° 10
B5: Grupo | C5: Grupo 2 – Nova Consulting
B6: Cliente | C6: Full Basics – PyME de indumentaria y textil (CABA)
B7: Proyecto evaluado | C7: Plataforma de atención omnicanal con IA (CRM omnicanal / mesa de ayuda)
B8: Proveedores | C8: ChatWoot vs. HubSpot Service Hub
B9: Fecha | C9: Junio 2026
B11: Contenido
B12: Este artefacto define la matriz RFP (aspectos, categorías e ítems con su ponderación y justificación) y las escalas de medición que se utilizarán para evaluar a los proveedores.

Sheet Aspectos y Ponderación
B2: Aspectos de evaluación y % de relevancia para Full Basics
B3: Aspecto (Nivel 0) | C3: Ponderación | D3: Justificación de la ponderación (caso Full Basics)
B4: Proveedor | C4: 0.15 | D4: Full Basics es una PyME sin área de IT interna: necesita un proveedor confiable, pero al ser un proyecto acotado y de bajo riesgo la madurez del proveedor pesa menos que el ajuste de la solución. Por eso 15%.
B5: Funcional | C5: 0.35 | D5: Aspecto de mayor peso (35%): el objetivo central es centralizar y profesionalizar la atención (WhatsApp como canal principal, omnicanalidad, tickets y automatización). El ajuste funcional define si se resuelve la brecha.
B6: Técnico | C6: 0.25 | D6: 25%: integrarse al stack actual (TiendaNube, Google Workspace, WhatsApp Business) y operar en la nube es importante para no sumar infraestructura, pero es habilitante, no el fin del proyecto.
B7: Económico | C7: 0.25 | D7: 25%: con recursos limitados, la sostenibilidad del costo (inicial y recurrente) es decisiva, a la par del aspecto técnico para no subordinar el ajuste funcional únicamente al precio.
B8: TOTAL | C8: =SUM(C4:C7) -> 1 | D8: La suma de los aspectos de Nivel 0 debe ser 100%.

Sheet Escalas
B2: Escalas de medición del grado de cumplimiento
B3: Misma graduación de puntaje (100/80/60/30/0) en las 4 áreas; cambia el requisito de cada nivel. La escala económica es objetiva: mide el % de desvío del costo relevado vs. el presupuesto de referencia.
B5: Escala FUNCIONAL | E5: Escala TÉCNICA | H5: Referencia
B6: Nivel (Puntaje) | C6: Requisito | E6: Nivel (Puntaje) | F6: Requisito | H6: Calificación | I6: Puntaje
B7: Excelente (100) | C7: Cumple nativamente la totalidad del requerimiento | E7: Excelente (100) | F7: Cumple completamente los requisitos técnicos | H7: Excelente | I7: 100
B8: Muy bueno (80) | C8: Cumple mediante parametrización o configuración simple | E8: Muy bueno (80) | F8: Cumple con ajustes menores de configuración | H8: Muy bueno | I8: 80
B9: Bueno (60) | C9: Cumple mediante integración estándar (API, plugin o conector) | E9: Bueno (60) | F9: Requiere desarrollos/integraciones de baja complejidad | H9: Bueno | I9: 60
B10: Regular (30) | C10: Cumple parcialmente; limitaciones funcionales relevantes | E10: Regular (30) | F10: Cumple parcialmente; restricciones técnicas significativas | H10: Regular | I10: 30
B11: Deficiente (0) | C11: No cumple ni existe forma razonable de implementarlo | E11: Deficiente (0) | F11: No cumple los requisitos técnicos | H11: Deficiente | I11: 0
B13: Escala PROVEEDOR | E13: Escala ECONÓMICA (% de desvío vs. presupuesto)
B14: Nivel (Puntaje) | C14: Requisito | E14: Nivel (Puntaje) | F14: Requisito
B15: Excelente (100) | C15: Alta trayectoria, soporte formal y amplia adopción | E15: Excelente (100) | F15: Costo ≤ presupuesto (desvío ≤ 0%)
B16: Muy bueno (80) | C16: Trayectoria consolidada y soporte adecuado | E16: Muy bueno (80) | F16: Hasta 10% por encima del presupuesto
B17: Bueno (60) | C17: Experiencia suficiente y soporte aceptable | E17: Bueno (60) | F17: Entre 10% y 25% por encima
B18: Regular (30) | C18: Experiencia limitada o soporte reducido | E18: Regular (30) | F18: Entre 25% y 50% por encima
B19: Deficiente (0) | C19: Sin referencias o soporte insuficiente | E19: Deficiente (0) | F19: Más de 50% por encima o inviable

Sheet RFP - Proveedor
B2: RFP – Aspecto PROVEEDOR (Ponderación Nivel 0: 15%)
B3: Peso global = % Aspecto × % Categoría (N1) × % Ítem (N2) · Aporte ponderado = Puntaje × Peso global | H3: ChatWoot | L3: HubSpot Service Hub
B4: Categoría (N1) / Ítem (N2) | C4: Pond. N1 | D4: Pond. N2 | E4: Peso global | F4: Descripción del ítem | G4: Justificación de la ponderación (Full Basics) | H4: Calificación | I4: Puntaje | J4: Aporte pond. | K4: Justificación de la calificación | L4: Calificación | M4: Puntaje | N4: Aporte pond. | O4: Justificación de la calificación
B5: ▸ A. Trayectoria y Experiencia | C5: 0.5 | F5: Madurez del proveedor y experiencia en implementaciones similares. | G5: Para una PyME sin IT interno, un proveedor probado reduce el riesgo de implementación.
B6: 1. Casos de éxito | D6: 0.4 | E6: =0.15*$C$5*D6 -> 0.03 | F6: Cantidad y relevancia de implementaciones similares. | G6: Valida que la solución funcione en contextos como el de Full Basics. | H6: Muy bueno | I6: =VLOOKUP(H6,Escalas!$H$7:$I$11,2,FALSE()) -> 80 | J6: =I6*E6 -> 2.4 | K6: Amplia adopción en PyMEs y proyectos open-source. | L6: Excelente | M6: =VLOOKUP(L6,Escalas!$H$7:$I$11,2,FALSE()) -> 100 | N6: =M6*E6 -> 3 | O6: Líder global con miles de casos de mesa de ayuda.
B7: 2. Años de experiencia | D7: 0.3 | E7: =0.15*$C$5*D7 -> 0.0225 | F7: Antigüedad del proveedor en el mercado. | G7: Refleja estabilidad y continuidad del soporte. | H7: Bueno | I7: =VLOOKUP(H7,Escalas!$H$7:$I$11,2,FALSE()) -> 60 | J7: =I7*E7 -> 1.35 | K7: Empresa más joven (2017) pero en crecimiento sostenido. | L7: Excelente | M7: =VLOOKUP(L7,Escalas!$H$7:$I$11,2,FALSE()) -> 100 | N7: =M7*E7 -> 2.25 | O7: Más de 15 años en el mercado (2006).
B8: 3. Presencia internacional | D8: 0.3 | E8: =0.15*$C$5*D8 -> 0.0225 | F8: Alcance geográfico y nivel de adopción. | G8: Indica vigencia y capacidad de soporte a largo plazo. | H8: Bueno | I8: =VLOOKUP(H8,Escalas!$H$7:$I$11,2,FALSE()) -> 60 | J8: =I8*E8 -> 1.35 | K8: Presencia global creciente, menor adopción corporativa. | L8: Excelente | M8: =VLOOKUP(L8,Escalas!$H$7:$I$11,2,FALSE()) -> 100 | N8: =M8*E8 -> 2.25 | O8: Presencia consolidada en múltiples regiones.
B9: ▸ B. Soporte y Comunidad | C9: 0.5 | F9: Asistencia, documentación y recursos para el usuario. | G9: Full Basics no tiene IT y dependerá del soporte/documentación del proveedor.
B10: 1. Soporte técnico | D10: 0.4 | E10: =0.15*$C$9*D10 -> 0.03 | F10: Disponibilidad y calidad del soporte. | G10: Reduce el tiempo de resolución sin equipo interno. | H10: Bueno | I10: =VLOOKUP(H10,Escalas!$H$7:$I$11,2,FALSE()) -> 60 | J10: =I10*E10 -> 1.8 | K10: Soporte por comunidad/documentación; formal en planes pagos. | L10: Muy bueno | M10: =VLOOKUP(L10,Escalas!$H$7:$I$11,2,FALSE()) -> 80 | N10: =M10*E10 -> 2.4 | O10: Soporte formal por chat/email según plan.
B11: 2. Comunidad y documentación | D11: 0.3 | E11: =0.15*$C$9*D11 -> 0.0225 | F11: Manuales, foros y documentación. | G11: Facilita la autogestión y reduce la dependencia. | H11: Excelente | I11: =VLOOKUP(H11,Escalas!$H$7:$I$11,2,FALSE()) -> 100 | J11: =I11*E11 -> 2.25 | K11: Comunidad open-source muy activa, documentación abundante. | L11: Muy bueno | M11: =VLOOKUP(L11,Escalas!$H$7:$I$11,2,FALSE()) -> 80 | N11: =M11*E11 -> 1.8 | O11: Documentación extensa y HubSpot Academy.
B12: 3. Capacitación disponible | D12: 0.3 | E12: =0.15*$C$9*D12 -> 0.0225 | F12: Recursos de entrenamiento. | G12: Acelera la adopción del equipo de atención. | H12: Bueno | I12: =VLOOKUP(H12,Escalas!$H$7:$I$11,2,FALSE()) -> 60 | J12: =I12*E12 -> 1.35 | K12: Recursos disponibles, más limitados que grandes proveedores. | L12: Muy bueno | M12: =VLOOKUP(L12,Escalas!$H$7:$I$11,2,FALSE()) -> 80 | N12: =M12*E12 -> 1.8 | O12: Academy con cursos y certificaciones gratuitas.
B13: TOTAL APORTE PROVEEDOR | J13: =J6+J7+J8+J10+J11+J12 -> 10.5 | K13: pts. sobre 100 del puntaje final | N13: =N6+N7+N8+N10+N11+N12 -> 13.5 | O13: pts. sobre 100 del puntaje final

Sheet RFP - Funcional
B2: RFP – Aspecto FUNCIONAL (Ponderación Nivel 0: 35%)
B3: Peso global = % Aspecto × % Categoría (N1) × % Ítem (N2) · Aporte ponderado = Puntaje × Peso global | H3: ChatWoot | L3: HubSpot Service Hub
B4: Categoría (N1) / Ítem (N2) | C4: Pond. N1 | D4: Pond. N2 | E4: Peso global | F4: Descripción del ítem | G4: Justificación de la ponderación (Full Basics) | H4: Calificación | I4: Puntaje | J4: Aporte pond. | K4: Justificación de la calificación | L4: Calificación | M4: Puntaje | N4: Aporte pond. | O4: Justificación de la calificación
B5: ▸ A. Gestión Omnicanal | C5: 0.4 | F5: Centralizar interacciones de múltiples canales en una plataforma. | G5: Brecha central de Full Basics: hoy la atención está dispersa (WhatsApp, Instagram, web).
B6: 1. Integración con WhatsApp | D6: 0.4 | E6: =0.35*$C$5*D6 -> 0.056 | F6: Gestión centralizada de WhatsApp Business. | G6: WhatsApp es el canal principal de ventas y atención. | H6: Muy bueno | I6: =VLOOKUP(H6,Escalas!$H$7:$I$11,2,FALSE()) -> 80 | J6: =I6*E6 -> 4.48 | K6: Integración con WhatsApp Business API. | L6: Muy bueno | M6: =VLOOKUP(L6,Escalas!$H$7:$I$11,2,FALSE()) -> 80 | N6: =M6*E6 -> 4.48 | O6: Integra WhatsApp según plan/conector.
B7: 2. Integración con otros canales | D7: 0.3 | E7: =0.35*$C$5*D7 -> 0.042 | F7: Instagram, web chat y email. | G7: También recibe consultas por Instagram y la tienda online. | H7: Bueno | I7: =VLOOKUP(H7,Escalas!$H$7:$I$11,2,FALSE()) -> 60 | J7: =I7*E7 -> 2.52 | K7: Integra web chat, Facebook e Instagram con conectores. | L7: Muy bueno | M7: =VLOOKUP(L7,Escalas!$H$7:$I$11,2,FALSE()) -> 80 | N7: =M7*E7 -> 3.36 | O7: Integración nativa con múltiples canales.
B8: 3. Bandeja unificada | D8: 0.3 | E8: =0.35*$C$5*D8 -> 0.042 | F8: Visualización centralizada de conversaciones. | G8: Permite que pocas personas atiendan todos los canales. | H8: Muy bueno | I8: =VLOOKUP(H8,Escalas!$H$7:$I$11,2,FALSE()) -> 80 | J8: =I8*E8 -> 3.36 | K8: Centraliza todo en una única interfaz. | L8: Muy bueno | M8: =VLOOKUP(L8,Escalas!$H$7:$I$11,2,FALSE()) -> 80 | N8: =M8*E8 -> 3.36 | O8: Bandeja compartida con seguimiento unificado.
B9: ▸ B. Gestión de la atención | C9: 0.35 | F9: Administración de consultas, reclamos y seguimiento. | G9: Full Basics necesita profesionalizar la atención sin aumentar la estructura.
B10: 1. Gestión de tickets | D10: 0.35 | E10: =0.35*$C$9*D10 -> 0.042875 | F10: Registro y seguimiento de consultas. | G10: Mejora el control sobre solicitudes pendientes. | H10: Bueno | I10: =VLOOKUP(H10,Escalas!$H$7:$I$11,2,FALSE()) -> 60 | J10: =I10*E10 -> 2.5725 | K10: Tickets orientados a soporte conversacional. | L10: Muy bueno | M10: =VLOOKUP(L10,Escalas!$H$7:$I$11,2,FALSE()) -> 80 | N10: =M10*E10 -> 3.43 | O10: Tickets avanzados con flujos y SLAs.
B11: 2. Historial de conversaciones | D11: 0.35 | E11: =0.35*$C$9*D11 -> 0.042875 | F11: Conservación del historial por cliente. | G11: Permite atención contextualizada. | H11: Muy bueno | I11: =VLOOKUP(H11,Escalas!$H$7:$I$11,2,FALSE()) -> 80 | J11: =I11*E11 -> 3.43 | K11: Historial completo por contacto. | L11: Muy bueno | M11: =VLOOKUP(L11,Escalas!$H$7:$I$11,2,FALSE()) -> 80 | N11: =M11*E11 -> 3.43 | O11: Historial integrado en la ficha CRM.
B12: 3. Asignación de agentes | D12: 0.3 | E12: =0.35*$C$9*D12 -> 0.03675 | F12: Distribución de conversaciones. | G12: Organiza el trabajo del pequeño equipo. | H12: Bueno | I12: =VLOOKUP(H12,Escalas!$H$7:$I$11,2,FALSE()) -> 60 | J12: =I12*E12 -> 2.205 | K12: Asignación manual y reglas básicas. | L12: Muy bueno | M12: =VLOOKUP(L12,Escalas!$H$7:$I$11,2,FALSE()) -> 80 | N12: =M12*E12 -> 2.94 | O12: Asignación automática y balanceo de carga.
B13: ▸ C. Automatización e IA | C13: 0.25 | F13: Automatización de respuestas y asistencia por IA. | G13: Busca reducir tareas repetitivas y responder fuera de horario sin sumar personal.
B14: 1. Chatbot / IA integrada | D14: 0.4 | E14: =0.35*$C$13*D14 -> 0.035 | F14: Asistencia automática por IA. | G14: Atención continua y escalable sin crecer en estructura. | H14: Bueno | I14: =VLOOKUP(H14,Escalas!$H$7:$I$11,2,FALSE()) -> 60 | J14: =I14*E14 -> 2.1 | K14: IA 'Captain' en planes pagos / vía APIs. | L14: Muy bueno | M14: =VLOOKUP(L14,Escalas!$H$7:$I$11,2,FALSE()) -> 80 | N14: =M14*E14 -> 2.8 | O14: IA nativa en la plataforma.
B15: 2. Automatización de respuestas | D15: 0.35 | E15: =0.35*$C$13*D15 -> 0.030625 | F15: Respuestas automáticas y flujos. | G15: Reduce la carga operativa en consultas frecuentes. | H15: Bueno | I15: =VLOOKUP(H15,Escalas!$H$7:$I$11,2,FALSE()) -> 60 | J15: =I15*E15 -> 1.8375 | K15: Automatizaciones por reglas y macros. | L15: Bueno | M15: =VLOOKUP(L15,Escalas!$H$7:$I$11,2,FALSE()) -> 60 | N15: =M15*E15 -> 1.8375 | O15: Automatizaciones (avanzadas en planes superiores).
B16: 3. Reglas automáticas de derivación | D16: 0.25 | E16: =0.35*$C$13*D16 -> 0.021875 | F16: Asignación automática por criterios. | G16: Optimiza la distribución del trabajo. | H16: Regular | I16: =VLOOKUP(H16,Escalas!$H$7:$I$11,2,FALSE()) -> 30 | J16: =I16*E16 -> 0.65625 | K16: Reglas de enrutamiento básicas. | L16: Regular | M16: =VLOOKUP(L16,Escalas!$H$7:$I$11,2,FALSE()) -> 30 | N16: =M16*E16 -> 0.65625 | O16: Derivación más rica pero requiere configuración avanzada.
B17: TOTAL APORTE FUNCIONAL | J17: =J6+J7+J8+J10+J11+J12+J14+J15+J16 -> 23.16125 | K17: pts. sobre 100 del puntaje final | N17: =N6+N7+N8+N10+N11+N12+N14+N15+N16 -> 26.29375 | O17: pts. sobre 100 del puntaje final

Sheet RFP - Técnico
B2: RFP – Aspecto TÉCNICO (Ponderación Nivel 0: 25%)
B3: Peso global = % Aspecto × % Categoría (N1) × % Ítem (N2) · Aporte ponderado = Puntaje × Peso global | H3: ChatWoot | L3: HubSpot Service Hub
B4: Categoría (N1) / Ítem (N2) | C4: Pond. N1 | D4: Pond. N2 | E4: Peso global | F4: Descripción del ítem | G4: Justificación de la ponderación (Full Basics) | H4: Calificación | I4: Puntaje | J4: Aporte pond. | K4: Justificación de la calificación | L4: Calificación | M4: Puntaje | N4: Aporte pond. | O4: Justificación de la calificación
B5: ▸ A. Integración | C5: 0.45 | F5: Interoperabilidad con los sistemas que ya usa Full Basics. | G5: Debe convivir con el stack actual (TiendaNube, Google Workspace, WhatsApp).
B6: 1. APIs disponibles | D6: 0.4 | E6: =0.25*$C$5*D6 -> 0.045 | F6: Disponibilidad y calidad de APIs. | G6: Habilita conectar la tienda online y futuras automatizaciones. | H6: Excelente | I6: =VLOOKUP(H6,Escalas!$H$7:$I$11,2,FALSE()) -> 100 | J6: =I6*E6 -> 4.5 | K6: APIs abiertas y bien documentadas (open-source). | L6: Excelente | M6: =VLOOKUP(L6,Escalas!$H$7:$I$11,2,FALSE()) -> 100 | N6: =M6*E6 -> 4.5 | O6: Ecosistema robusto de APIs REST.
B7: 2. Integración con WhatsApp Business | D7: 0.3 | E7: =0.25*$C$5*D7 -> 0.03375 | F7: Compatibilidad con el canal principal. | G7: WhatsApp es crítico para la operación diaria. | H7: Muy bueno | I7: =VLOOKUP(H7,Escalas!$H$7:$I$11,2,FALSE()) -> 80 | J7: =I7*E7 -> 2.7 | K7: Integración orientada a omnicanalidad. | L7: Bueno | M7: =VLOOKUP(L7,Escalas!$H$7:$I$11,2,FALSE()) -> 60 | N7: =M7*E7 -> 2.025 | O7: Requiere conector/plan específico.
B8: 3. Integración con Google Workspace | D8: 0.3 | E8: =0.25*$C$5*D8 -> 0.03375 | F8: Compatibilidad con Gmail, Drive y Sheets. | G8: Herramientas que Full Basics ya utiliza. | H8: Bueno | I8: =VLOOKUP(H8,Escalas!$H$7:$I$11,2,FALSE()) -> 60 | J8: =I8*E8 -> 2.025 | K8: Integra con Google vía APIs/conectores. | L8: Muy bueno | M8: =VLOOKUP(L8,Escalas!$H$7:$I$11,2,FALSE()) -> 80 | N8: =M8*E8 -> 2.7 | O8: Integración nativa con Gmail, Calendar y Drive.
B9: ▸ B. Infraestructura | C9: 0.3 | F9: Requerimientos tecnológicos para operar. | G9: Se busca minimizar inversión en infraestructura propia (escenario SaaS).
B10: 1. Modalidad Cloud/SaaS | D10: 0.5 | E10: =0.25*$C$9*D10 -> 0.0375 | F10: Operación en la nube. | G10: Reduce costos operativos y administración. | H10: Muy bueno | I10: =VLOOKUP(H10,Escalas!$H$7:$I$11,2,FALSE()) -> 80 | J10: =I10*E10 -> 3 | K10: Disponible en SaaS y autogestionado. | L10: Muy bueno | M10: =VLOOKUP(L10,Escalas!$H$7:$I$11,2,FALSE()) -> 80 | N10: =M10*E10 -> 3 | O10: 100% SaaS administrado por el proveedor.
B11: 2. Escalabilidad técnica | D11: 0.25 | E11: =0.25*$C$9*D11 -> 0.01875 | F11: Capacidad de crecer en usuarios y volumen. | G11: Acompaña el objetivo de escalar +30% sin sumar estructura. | H11: Bueno | I11: =VLOOKUP(H11,Escalas!$H$7:$I$11,2,FALSE()) -> 60 | J11: =I11*E11 -> 1.125 | K11: Escalable para PyMEs/medianas vía cloud. | L11: Muy bueno | M11: =VLOOKUP(L11,Escalas!$H$7:$I$11,2,FALSE()) -> 80 | N11: =M11*E11 -> 1.5 | O11: Escala de pequeñas a grandes organizaciones.
B12: 3. Requerimientos de hardware | D12: 0.25 | E12: =0.25*$C$9*D12 -> 0.01875 | F12: Equipamiento adicional necesario. | G12: Se busca reutilizar las PCs actuales. | H12: Muy bueno | I12: =VLOOKUP(H12,Escalas!$H$7:$I$11,2,FALSE()) -> 80 | J12: =I12*E12 -> 1.5 | K12: En SaaS no requiere hardware (VPS si se autohospeda). | L12: Excelente | M12: =VLOOKUP(L12,Escalas!$H$7:$I$11,2,FALSE()) -> 100 | N12: =M12*E12 -> 1.875 | O12: No requiere infraestructura propia.
B13: ▸ C. Seguridad | C13: 0.25 | F13: Protección y disponibilidad de la información. | G13: La información de clientes y ventas es un activo crítico.
B14: 1. Gestión de usuarios y permisos | D14: 0.4 | E14: =0.25*$C$13*D14 -> 0.025 | F14: Control de accesos por perfiles. | G14: Protege información sensible. | H14: Bueno | I14: =VLOOKUP(H14,Escalas!$H$7:$I$11,2,FALSE()) -> 60 | J14: =I14*E14 -> 1.5 | K14: Perfiles y permisos configurables. | L14: Bueno | M14: =VLOOKUP(L14,Escalas!$H$7:$I$11,2,FALSE()) -> 60 | N14: =M14*E14 -> 1.5 | O14: Roles y permisos (avanzados en planes superiores).
B15: 2. Backups automáticos | D15: 0.3 | E15: =0.25*$C$13*D15 -> 0.01875 | F15: Respaldo y recuperación de datos. | G15: Garantiza continuidad ante incidentes. | H15: Bueno | I15: =VLOOKUP(H15,Escalas!$H$7:$I$11,2,FALSE()) -> 60 | J15: =I15*E15 -> 1.125 | K15: Gestionado en SaaS según modalidad. | L15: Muy bueno | M15: =VLOOKUP(L15,Escalas!$H$7:$I$11,2,FALSE()) -> 80 | N15: =M15*E15 -> 1.5 | O15: Respaldos automáticos por la plataforma.
B16: 3. Disponibilidad del servicio | D16: 0.3 | E16: =0.25*$C$13*D16 -> 0.01875 | F16: Nivel de disponibilidad/SLA. | G16: Reduce interrupciones que afectan ventas. | H16: Bueno | I16: =VLOOKUP(H16,Escalas!$H$7:$I$11,2,FALSE()) -> 60 | J16: =I16*E16 -> 1.125 | K16: Alta disponibilidad, según infraestructura. | L16: Muy bueno | M16: =VLOOKUP(L16,Escalas!$H$7:$I$11,2,FALSE()) -> 80 | N16: =M16*E16 -> 1.5 | O16: SLA empresariales y alta disponibilidad.
B17: TOTAL APORTE TÉCNICO | J17: =J6+J7+J8+J10+J11+J12+J14+J15+J16 -> 18.6 | K17: pts. sobre 100 del puntaje final | N17: =N6+N7+N8+N10+N11+N12+N14+N15+N16 -> 20.1 | O17: pts. sobre 100 del puntaje final

Sheet RFP - Económico
B2: RFP – Aspecto ECONÓMICO (Ponderación Nivel 0: 25%) · Calificación objetiva por % de desvío
B3: Niveles y ponderación | G3: ChatWoot | M3: HubSpot Service Hub
B4: Categoría (N1) / Ítem (N2) | C4: Pond. N1 | D4: Pond. N2 | E4: Peso global | F4: Descripción / métrica | G4: Presup. ref. (USD) | H4: Relevado (USD) | I4: % desvío | J4: Calificación | K4: Puntaje | L4: Aporte pond. | M4: Relevado (USD) | N4: % desvío | O4: Calificación | P4: Puntaje | Q4: Aporte pond.
B5: ▸ A. Costos Iniciales | C5: 0.4 | F5: Inversiones para implementar la solución.
B6: 1. Costo de implementación | D6: 0.5 | E6: =0.25*$C$5*D6 -> 0.05 | F6: Consultoría+instalación+customización+migración (one-time). | G6: 3000 | H6: 2950 | I6: =(H6-G6)/G6 -> -0.016666667 | J6: =IF(I6<=0,"Excelente",IF(I6<=0.1,"Muy bueno",IF(I6<=0.25,"Bueno",IF(I6<=0.5,"Regular","Deficiente")))) -> Excelente | K6: =VLOOKUP(J6,Escalas!$H$7:$I$11,2,FALSE()) -> 100 | L6: =K6*E6 -> 5 | M6: 4250 | N6: =(M6-G6)/G6 -> 0.41666667 | O6: =IF(N6<=0,"Excelente",IF(N6<=0.1,"Muy bueno",IF(N6<=0.25,"Bueno",IF(N6<=0.5,"Regular","Deficiente")))) -> Regular | P6: =VLOOKUP(O6,Escalas!$H$7:$I$11,2,FALSE()) -> 30 | Q6: =P6*E6 -> 1.5
B7: 2. Costo de capacitación | D7: 0.25 | E7: =0.25*$C$5*D7 -> 0.025 | F7: Formación inicial de usuarios (anual). | G7: 300 | H7: 250 | I7: =(H7-G7)/G7 -> -0.16666667 | J7: =IF(I7<=0,"Excelente",IF(I7<=0.1,"Muy bueno",IF(I7<=0.25,"Bueno",IF(I7<=0.5,"Regular","Deficiente")))) -> Excelente | K7: =VLOOKUP(J7,Escalas!$H$7:$I$11,2,FALSE()) -> 100 | L7: =K7*E7 -> 2.5 | M7: 400 | N7: =(M7-G7)/G7 -> 0.33333333 | O7: =IF(N7<=0,"Excelente",IF(N7<=0.1,"Muy bueno",IF(N7<=0.25,"Bueno",IF(N7<=0.5,"Regular","Deficiente")))) -> Regular | P7: =VLOOKUP(O7,Escalas!$H$7:$I$11,2,FALSE()) -> 30 | Q7: =P7*E7 -> 0.75
B8: 3. Costos de infraestructura | D8: 0.25 | E8: =0.25*$C$5*D8 -> 0.025 | F8: Hardware/infra complementaria (one-time). | G8: 300 | H8: 150 | I8: =(H8-G8)/G8 -> -0.5 | J8: =IF(I8<=0,"Excelente",IF(I8<=0.1,"Muy bueno",IF(I8<=0.25,"Bueno",IF(I8<=0.5,"Regular","Deficiente")))) -> Excelente | K8: =VLOOKUP(J8,Escalas!$H$7:$I$11,2,FALSE()) -> 100 | L8: =K8*E8 -> 2.5 | M8: 0 | N8: =(M8-G8)/G8 -> -1 | O8: =IF(N8<=0,"Excelente",IF(N8<=0.1,"Muy bueno",IF(N8<=0.25,"Bueno",IF(N8<=0.5,"Regular","Deficiente")))) -> Excelente | P8: =VLOOKUP(O8,Escalas!$H$7:$I$11,2,FALSE()) -> 100 | Q8: =P8*E8 -> 2.5
B9: ▸ B. Costos Operativos | C9: 0.6 | F9: Costos recurrentes de la solución.
B10: 1. Licenciamiento anual | D10: 0.4 | E10: =0.25*$C$9*D10 -> 0.06 | F10: Suscripción anual (3 agentes/seats). | G10: 1800 | H10: 1404 | I10: =(H10-G10)/G10 -> -0.22 | J10: =IF(I10<=0,"Excelente",IF(I10<=0.1,"Muy bueno",IF(I10<=0.25,"Bueno",IF(I10<=0.5,"Regular","Deficiente")))) -> Excelente | K10: =VLOOKUP(J10,Escalas!$H$7:$I$11,2,FALSE()) -> 100 | L10: =K10*E10 -> 6 | M10: 3600 | N10: =(M10-G10)/G10 -> 1 | O10: =IF(N10<=0,"Excelente",IF(N10<=0.1,"Muy bueno",IF(N10<=0.25,"Bueno",IF(N10<=0.5,"Regular","Deficiente")))) -> Deficiente | P10: =VLOOKUP(O10,Escalas!$H$7:$I$11,2,FALSE()) -> 0 | Q10: =P10*E10 -> 0
B11: 2. Costos de mantenimiento | D11: 0.3 | E11: =0.25*$C$9*D11 -> 0.045 | F11: Soporte/administración anual. | G11: 400 | H11: 300 | I11: =(H11-G11)/G11 -> -0.25 | J11: =IF(I11<=0,"Excelente",IF(I11<=0.1,"Muy bueno",IF(I11<=0.25,"Bueno",IF(I11<=0.5,"Regular","Deficiente")))) -> Excelente | K11: =VLOOKUP(J11,Escalas!$H$7:$I$11,2,FALSE()) -> 100 | L11: =K11*E11 -> 4.5 | M11: 0 | N11: =(M11-G11)/G11 -> -1 | O11: =IF(N11<=0,"Excelente",IF(N11<=0.1,"Muy bueno",IF(N11<=0.25,"Bueno",IF(N11<=0.5,"Regular","Deficiente")))) -> Excelente | P11: =VLOOKUP(O11,Escalas!$H$7:$I$11,2,FALSE()) -> 100 | Q11: =P11*E11 -> 4.5
B12: 3. Escalabilidad económica | D12: 0.3 | E12: =0.25*$C$9*D12 -> 0.045 | F12: Costo de agregar 1 usuario/mes (USD). | G12: 40 | H12: 39 | I12: =(H12-G12)/G12 -> -0.025 | J12: =IF(I12<=0,"Excelente",IF(I12<=0.1,"Muy bueno",IF(I12<=0.25,"Bueno",IF(I12<=0.5,"Regular","Deficiente")))) -> Excelente | K12: =VLOOKUP(J12,Escalas!$H$7:$I$11,2,FALSE()) -> 100 | L12: =K12*E12 -> 4.5 | M12: 100 | N12: =(M12-G12)/G12 -> 1.5 | O12: =IF(N12<=0,"Excelente",IF(N12<=0.1,"Muy bueno",IF(N12<=0.25,"Bueno",IF(N12<=0.5,"Regular","Deficiente")))) -> Deficiente | P12: =VLOOKUP(O12,Escalas!$H$7:$I$11,2,FALSE()) -> 0 | Q12: =P12*E12 -> 0
B13: TOTAL APORTE ECONÓMICO | L13: =L6+L7+L8+L10+L11+L12 -> 25 | Q13: =Q6+Q7+Q8+Q10+Q11+Q12 -> 9.25
